zsql.py
zsql-1.0.2.dist-info/METADATA
zsql-1.0.2.dist-info/RECORD
zsql-1.0.2.dist-info/WHEEL
zsql-1.0.2.dist-info/top_level.txt
